pytwits/__init__.py
pytwits/classes.py
pytwits/const.py
pytwits/exceptions.py
pytwits/requestor.py
pytwits/stocktwits.py
PyTwits-1.0.1.dist-info/LICENSE.md
PyTwits-1.0.1.dist-info/METADATA
PyTwits-1.0.1.dist-info/WHEEL
PyTwits-1.0.1.dist-info/top_level.txt
PyTwits-1.0.1.dist-info/RECORD
