Metadata-Version: 2.1
Name: PyTwits
Version: 1.0.1
Summary: PyTwits is a REST-API Wrapper for StockTwits.
Home-page: https://github.com/tbienias/PyTwits
Author: Tim Bienias
Author-email: 
License: UNKNOWN
Platform: UNKNOWN
Classifier: Programming Language :: Python :: 3
Classifier: License :: OSI Approved :: MIT License
Classifier: Operating System :: OS Independent
Requires-Dist: requests
